npstreams/__init__.py
npstreams/array_stream.py
npstreams/array_utils.py
npstreams/benchmarks.py
npstreams/cuda.py
npstreams/flow.py
npstreams/iter_utils.py
npstreams/linalg.py
npstreams/numerics.py
npstreams/parallel.py
npstreams/reduce.py
npstreams/stacking.py
npstreams/stats.py
npstreams/utils.py
npstreams/tests/__init__.py
npstreams/tests/test_array_stream.py
npstreams/tests/test_array_utils.py
npstreams/tests/test_cuda.py
npstreams/tests/test_flow.py
npstreams/tests/test_iter_utils.py
npstreams/tests/test_linalg.py
npstreams/tests/test_numerics.py
npstreams/tests/test_parallel.py
npstreams/tests/test_reduce.py
npstreams/tests/test_stacking.py
npstreams/tests/test_stats.py
npstreams/tests/data/test_data1.npy
npstreams/tests/data/test_data2.npy
npstreams/tests/data/test_data3.npy
npstreams-1.7.0.dist-info/LICENSE.txt
npstreams-1.7.0.dist-info/METADATA
npstreams-1.7.0.dist-info/WHEEL
npstreams-1.7.0.dist-info/top_level.txt
npstreams-1.7.0.dist-info/RECORD
