Metadata-Version: 2.1
Name: npstreams
Version: 1.7.0
Summary: Streaming operations on NumPy arrays
Home-page: UNKNOWN
Author: Laurent P. René de Cotret
Author-email: laurent.renedecotret@mail.mcgill.ca
Maintainer: Laurent P. René de Cotret
Maintainer-email: laurent.renedecotret@mail.mcgill.ca
License: BSD
Download-URL: http://github.com/LaurentRDC/npstreams
Keywords: streaming,numpy,math
Platform: UNKNOWN
Classifier: Environment :: Console
Classifier: Intended Audience :: Science/Research
Classifier: Topic :: Scientific/Engineering
Classifier: License :: OSI Approved :: BSD License
Classifier: Natural Language :: English
Classifier: Operating System :: OS Independent
Classifier: Programming Language :: Python
Classifier: Programming Language :: Python :: 3.7
Classifier: Programming Language :: Python :: 3.8
Classifier: Programming Language :: Python :: 3.9
Requires-Python: >=3.7
License-File: LICENSE.txt
Requires-Dist: numpy<3,>=1.17
